{
  "summary": [
    {
      "id": 1,
      "amount": 1000
    },
    {
      "id": 2,
      "value": 1716
    },
    {
      "id": 3,
      "value": 331.36
    },
    {
      "id": 4,
      "value": 165.68
    },
    {
      "id": 5,
      "value": 165.68
    },
    {
      "id": 6,
      "value": 248.52
    }
  ],
  "income": [
    {
      "id": 1,
      "value": 7000
    },
    {
      "id": 2,
      "value": 3000
    },
    {
      "id": 3,
      "value": 10000
    }
  ],
  "expenses": [
    {
      "id": 1,
      "name": "percentage",
      "value": 17
    },
    {
      "id": 2,
      "name": "sum",
      "value": 1717
    },
    {
      "id": 3,
      "name": "Rest",
      "amount": 8283
    },
    {
      "id": 4,
      "name": "Mieszkanie",
      "price": 1000
    },
    {
      "id": 5,
      "name": "Jedzenie",
      "price": 456
    },
    {
      "id": 6,
      "name": "Prąd",
      "price": 54
    },
    {
      "id": 7,
      "name": "Woda",
      "price": 59
    },
    {
      "id": 8,
      "name": "Rata za odkurzacz",
      "price": 96
    },
    {
      "id": 9,
      "name": "Netflix",
      "price": 52
    },
    {
      "name": "gerdgbverb",
      "price": 0,
      "id": 10
    }
  ],
  "expansion": [
    {
      "id": 1,
      "percent": 6,
      "amount": 165.66
    },
    {
      "id": 2,
      "percent": 6,
      "amount": 496.98
    },
    {
      "id": 3,
      "percent": 2,
      "amount": 165.66
    },
    {
      "id": 4,
      "percent": 3,
      "amount": 248.49
    }
  ],
  "Styczen": {
    "income": 3860,
    "expenses": 1928,
    "savings": 251.16,
    "pleasure": 115.92,
    "investments": 367.08,
    "education": 753.48
  },
  "Luty": {
    "income": 3929,
    "expenses": 1864,
    "savings": 289.1,
    "pleasure": 82.6,
    "investments": 206.5,
    "education": 1218.35
  },
  "Marzec": {
    "income": 3759,
    "expenses": 2098,
    "savings": 448.47,
    "pleasure": 548.13,
    "investments": 99.66,
    "education": 249.15
  },
  "Kwiecien": {
    "income": 4222,
    "expenses": 2316,
    "savings": 590.86,
    "pleasure": 209.66,
    "investments": 95.3,
    "education": 285.9
  },
  "Maj": {
    "income": 9059,
    "expenses": 2429,
    "savings": 1856.4,
    "pleasure": 663,
    "investments": 1790.1,
    "education": 265.2
  },
  "Czerwiec": {
    "income": 10000,
    "expenses": 1717,
    "savings": 165.66,
    "pleasure": 496.98,
    "investments": 165.66,
    "education": 248.49
  },
  "Lipiec": {
    "income": 8909,
    "expenses": 3010,
    "savings": 1297.78,
    "pleasure": 825.86,
    "investments": 884.85,
    "education": 530.91
  },
  "Sierpien": {
    "income": 9254,
    "expenses": 289,
    "savings": 717.2,
    "pleasure": 986.15,
    "investments": 717.2,
    "education": 986.15
  },
  "Wrzesien": {
    "income": 4542,
    "expenses": 435,
    "savings": 369.63,
    "pleasure": 205.35,
    "investments": 123.21,
    "education": 574.98
  },
  "Pazdziernik": {
    "income": 8909,
    "expenses": 3010,
    "savings": 1297.78,
    "pleasure": 825.86,
    "investments": 884.85,
    "education": 530.91
  },
  "Listopad": {
    "income": 5000,
    "expenses": 345,
    "savings": 46.55,
    "pleasure": 139.65,
    "investments": 93.1,
    "education": 139.65
  },
  "Grudzien": {
    "income": 7600,
    "expenses": 4669,
    "savings": 146.55,
    "pleasure": 87.93,
    "investments": 58.62,
    "education": 175.86
  }
}